{
    "standard" :  {
        "8":{
        "CEP_a":146,
        "EGES_a":11,
        "CEP_b":186,
        "EGES_b":16,
        "CEP_c":386,
        "EGES_c":44,
        "CEP_d":505,
        "EGES_d":68,
        "CEP_e":622,
        "EGES_e":90,
        "CEP_f":739,
        "EGES_f":122
        },
        "9":{
        "CEP_a":134,
        "EGES_a":11,
        "CEP_b":174,
        "EGES_b":16,
        "CEP_c":355,
        "EGES_c":42,
        "CEP_d":464,
        "EGES_d":65,
        "CEP_e":574,
        "EGES_e":87,
        "CEP_f":685,
        "EGES_f":118
        },
        "10":{
        "CEP_a":124,
        "EGES_a":10,
        "CEP_b":164,
        "EGES_b":15,
        "CEP_c":329,
        "EGES_c":40,
        "CEP_d":428,
        "EGES_d":62,
        "CEP_e":533,
        "EGES_e":84,
        "CEP_f":640,
        "EGES_f":115
        },
        "11":{
        "CEP_a":117,
        "EGES_a":10,
        "CEP_b":157,
        "EGES_b":15,
        "CEP_c":311,
        "EGES_c":39,
        "CEP_d":403,
        "EGES_d":61,
        "CEP_e":503,
        "EGES_e":82,
        "CEP_f":607,
        "EGES_f":113
        },
        "12":{
        "CEP_a":112,
        "EGES_a":9,
        "CEP_b":152,
        "EGES_b":14,
        "CEP_c":296,
        "EGES_c":38,
        "CEP_d":381,
        "EGES_d":59,
        "CEP_e":478,
        "EGES_e":81,
        "CEP_f":578,
        "EGES_f":111
        },
        "13":{
        "CEP_a":108,
        "EGES_a":9,
        "CEP_b":148,
        "EGES_b":14,
        "CEP_c":283,
        "EGES_c":37,
        "CEP_d":363,
        "EGES_d":58,
        "CEP_e":456,
        "EGES_e":79,
        "CEP_f":554,
        "EGES_f":110
        },
        "14":{
        "CEP_a":104,
        "EGES_a":9,
        "CEP_b":144,
        "EGES_b":14,
        "CEP_c":273,
        "EGES_c":37,
        "CEP_d":348,
        "EGES_d":58,
        "CEP_e":437,
        "EGES_e":78,
        "CEP_f":532,
        "EGES_f":108
        },
        "15":{
        "CEP_a":100,
        "EGES_a":8,
        "CEP_b":140,
        "EGES_b":13,
        "CEP_c":263,
        "EGES_c":36,
        "CEP_d":333,
        "EGES_d":56,
        "CEP_e":421,
        "EGES_e":76,
        "CEP_f":514,
        "EGES_f":107
        },
        "16":{
        "CEP_a":97,
        "EGES_a":8,
        "CEP_b":137,
        "EGES_b":13,
        "CEP_c":255,
        "EGES_c":35,
        "CEP_d":325,
        "EGES_d":55,
        "CEP_e":412,
        "EGES_e":76,
        "CEP_f":504,
        "EGES_f":106
        },
        "17":{
        "CEP_a":95,
        "EGES_a":8,
        "CEP_b":135,
        "EGES_b":13,
        "CEP_c":248,
        "EGES_c":35,
        "CEP_d":318,
        "EGES_d":55,
        "CEP_e":404,
        "EGES_e":75,
        "CEP_f":496,
        "EGES_f":105
        },
        "18":{
        "CEP_a":92,
        "EGES_a":8,
        "CEP_b":132,
        "EGES_b":13,
        "CEP_c":241,
        "EGES_c":34,
        "CEP_d":311,
        "EGES_d":54,
        "CEP_e":397,
        "EGES_e":75,
        "CEP_f":489,
        "EGES_f":105
        },
        "19":{
        "CEP_a":90,
        "EGES_a":8,
        "CEP_b":130,
        "EGES_b":13,
        "CEP_c":235,
        "EGES_c":34,
        "CEP_d":305,
        "EGES_d":54,
        "CEP_e":390,
        "EGES_e":74,
        "CEP_f":482,
        "EGES_f":105
        },
        "20":{
        "CEP_a":88,
        "EGES_a":8,
        "CEP_b":128,
        "EGES_b":13,
        "CEP_c":230,
        "EGES_c":34,
        "CEP_d":300,
        "EGES_d":54,
        "CEP_e":385,
        "EGES_e":74,
        "CEP_f":476,
        "EGES_f":104
        },
        "21":{
        "CEP_a":87,
        "EGES_a":8,
        "CEP_b":127,
        "EGES_b":13,
        "CEP_c":225,
        "EGES_c":33,
        "CEP_d":295,
        "EGES_d":53,
        "CEP_e":380,
        "EGES_e":74,
        "CEP_f":471,
        "EGES_f":104
        },
        "22":{
        "CEP_a":85,
        "EGES_a":7,
        "CEP_b":125,
        "EGES_b":12,
        "CEP_c":221,
        "EGES_c":33,
        "CEP_d":291,
        "EGES_d":53,
        "CEP_e":375,
        "EGES_e":73,
        "CEP_f":466,
        "EGES_f":103
        },
        "23":{
        "CEP_a":84,
        "EGES_a":7,
        "CEP_b":124,
        "EGES_b":12,
        "CEP_c":217,
        "EGES_c":33,
        "CEP_d":287,
        "EGES_d":53,
        "CEP_e":371,
        "EGES_e":73,
        "CEP_f":462,
        "EGES_f":103
        },
        "24":{
        "CEP_a":82,
        "EGES_a":7,
        "CEP_b":122,
        "EGES_b":12,
        "CEP_c":214,
        "EGES_c":33,
        "CEP_d":284,
        "EGES_d":53,
        "CEP_e":367,
        "EGES_e":73,
        "CEP_f":458,
        "EGES_f":103
        },
        "25":{
        "CEP_a":81,
        "EGES_a":7,
        "CEP_b":121,
        "EGES_b":12,
        "CEP_c":210,
        "EGES_c":32,
        "CEP_d":280,
        "EGES_d":52,
        "CEP_e":363,
        "EGES_e":73,
        "CEP_f":454,
        "EGES_f":103
        },
        "26":{
        "CEP_a":80,
        "EGES_a":7,
        "CEP_b":120,
        "EGES_b":12,
        "CEP_c":207,
        "EGES_c":32,
        "CEP_d":277,
        "EGES_d":52,
        "CEP_e":360,
        "EGES_e":72,
        "CEP_f":451,
        "EGES_f":103
        },
        "27":{
        "CEP_a":79,
        "EGES_a":7,
        "CEP_b":119,
        "EGES_b":12,
        "CEP_c":204,
        "EGES_c":32,
        "CEP_d":274,
        "EGES_d":52,
        "CEP_e":357,
        "EGES_e":72,
        "CEP_f":447,
        "EGES_f":102
        },
        "28":{
        "CEP_a":78,
        "EGES_a":7,
        "CEP_b":118,
        "EGES_b":12,
        "CEP_c":202,
        "EGES_c":32,
        "CEP_d":272,
        "EGES_d":52,
        "CEP_e":354,
        "EGES_e":72,
        "CEP_f":444,
        "EGES_f":102
        },
        "29":{
        "CEP_a":77,
        "EGES_a":7,
        "CEP_b":117,
        "EGES_b":12,
        "CEP_c":199,
        "EGES_c":32,
        "CEP_d":269,
        "EGES_d":52,
        "CEP_e":351,
        "EGES_e":72,
        "CEP_f":442,
        "EGES_f":102
        },
        "30":{
        "CEP_a":76,
        "EGES_a":7,
        "CEP_b":116,
        "EGES_b":12,
        "CEP_c":197,
        "EGES_c":32,
        "CEP_d":267,
        "EGES_d":52,
        "CEP_e":349,
        "EGES_e":72,
        "CEP_f":439,
        "EGES_f":102
        },
        "31":{
        "CEP_a":76,
        "EGES_a":7,
        "CEP_b":116,
        "EGES_b":12,
        "CEP_c":195,
        "EGES_c":31,
        "CEP_d":265,
        "EGES_d":51,
        "CEP_e":346,
        "EGES_e":72,
        "CEP_f":437,
        "EGES_f":102
        },
        "32":{
        "CEP_a":75,
        "EGES_a":7,
        "CEP_b":115,
        "EGES_b":12,
        "CEP_c":193,
        "EGES_c":31,
        "CEP_d":263,
        "EGES_d":51,
        "CEP_e":344,
        "EGES_e":71,
        "CEP_f":434,
        "EGES_f":101
        },
        "33":{
        "CEP_a":74,
        "EGES_a":7,
        "CEP_b":114,
        "EGES_b":12,
        "CEP_c":191,
        "EGES_c":31,
        "CEP_d":261,
        "EGES_d":51,
        "CEP_e":342,
        "EGES_e":71,
        "CEP_f":432,
        "EGES_f":101
        },
        "34":{
        "CEP_a":74,
        "EGES_a":7,
        "CEP_b":114,
        "EGES_b":12,
        "CEP_c":189,
        "EGES_c":31,
        "CEP_d":259,
        "EGES_d":51,
        "CEP_e":340,
        "EGES_e":71,
        "CEP_f":430,
        "EGES_f":101
        },
        "35":{
        "CEP_a":73,
        "EGES_a":7,
        "CEP_b":113,
        "EGES_b":12,
        "CEP_c":188,
        "EGES_c":31,
        "CEP_d":258,
        "EGES_d":51,
        "CEP_e":338,
        "EGES_e":71,
        "CEP_f":428,
        "EGES_f":101
        },
        "36":{
        "CEP_a":72,
        "EGES_a":7,
        "CEP_b":112,
        "EGES_b":12,
        "CEP_c":186,
        "EGES_c":31,
        "CEP_d":256,
        "EGES_d":51,
        "CEP_e":337,
        "EGES_e":71,
        "CEP_f":427,
        "EGES_f":101
        },
        "37":{
        "CEP_a":72,
        "EGES_a":7,
        "CEP_b":112,
        "EGES_b":12,
        "CEP_c":185,
        "EGES_c":31,
        "CEP_d":255,
        "EGES_d":51,
        "CEP_e":335,
        "EGES_e":71,
        "CEP_f":425,
        "EGES_f":101
        },
        "38":{
        "CEP_a":71,
        "EGES_a":7,
        "CEP_b":111,
        "EGES_b":12,
        "CEP_c":183,
        "EGES_c":31,
        "CEP_d":253,
        "EGES_d":51,
        "CEP_e":333,
        "EGES_e":71,
        "CEP_f":423,
        "EGES_f":101
        },
        "39":{
        "CEP_a":71,
        "EGES_a":7,
        "CEP_b":111,
        "EGES_b":12,
        "CEP_c":182,
        "EGES_c":31,
        "CEP_d":252,
        "EGES_d":51,
        "CEP_e":332,
        "EGES_e":71,
        "CEP_f":422,
        "EGES_f":101
        },
        "40":{
        "CEP_a":70,
        "EGES_a":6,
        "CEP_b":110,
        "EGES_b":11,
        "CEP_c":180,
        "EGES_c":30,
        "CEP_d":250,
        "EGES_d":50,
        "CEP_e":330,
        "EGES_e":70,
        "CEP_f":420,
        "EGES_f":100
        }
    },
    "altitude": {
        "8":{
            "CEP_e":682,
            "EGES_e":100,
            "CEP_f":819,
            "EGES_f":132
        },
        "9":{
            "CEP_e":634,
            "EGES_e":97,
            "CEP_f":765,
            "EGES_f":128
        },
        "10":{
            "CEP_e":593,
            "EGES_e":94,
            "CEP_f":720,
            "EGES_f":125
        },
        "11":{
            "CEP_e":563,
            "EGES_e":92,
            "CEP_f":687,
            "EGES_f":123
        },
        "12":{
            "CEP_e":538,
            "EGES_e":91,
            "CEP_f":658,
            "EGES_f":121
        },
        "13":{
            "CEP_e":516,
            "EGES_e":89,
            "CEP_f":634,
            "EGES_f":120
        },
        "14":{
            "CEP_e":497,
            "EGES_e":88,
            "CEP_f":612,
            "EGES_f":118
        },
        "15":{
            "CEP_e":481,
            "EGES_e":86,
            "CEP_f":594,
            "EGES_f":117
        },
        "16":{
            "CEP_e":472,
            "EGES_e":86,
            "CEP_f":584,
            "EGES_f":116
        },
        "17":{
            "CEP_e":464,
            "EGES_e":85,
            "CEP_f":576,
            "EGES_f":115
        },
        "18":{
            "CEP_e":457,
            "EGES_e":85,
            "CEP_f":569,
            "EGES_f":115
        },
        "19":{
            "CEP_e":450,
            "EGES_e":84,
            "CEP_f":562,
            "EGES_f":115
        },
        "20":{
            "CEP_e":445,
            "EGES_e":84,
            "CEP_f":556,
            "EGES_f":114
        },
        "21":{
            "CEP_e":440,
            "EGES_e":84,
            "CEP_f":551,
            "EGES_f":114
        },
        "22":{
            "CEP_e":435,
            "EGES_e":83,
            "CEP_f":546,
            "EGES_f":113
        },
        "23":{
            "CEP_e":431,
            "EGES_e":83,
            "CEP_f":542,
            "EGES_f":113
        },
        "24":{
            "CEP_e":427,
            "EGES_e":83,
            "CEP_f":538,
            "EGES_f":113
        },
        "25":{
            "CEP_e":423,
            "EGES_e":83,
            "CEP_f":534,
            "EGES_f":113
        },
        "26":{
            "CEP_e":420,
            "EGES_e":82,
            "CEP_f":531,
            "EGES_f":113
        },
        "27":{
            "CEP_e":417,
            "EGES_e":82,
            "CEP_f":527,
            "EGES_f":112
        },
        "28":{
            "CEP_e":414,
            "EGES_e":82,
            "CEP_f":524,
            "EGES_f":112
        },
        "29":{
            "CEP_e":411,
            "EGES_e":82,
            "CEP_f":522,
            "EGES_f":112
        },
        "30":{
            "CEP_e":409,
            "EGES_e":82,
            "CEP_f":519,
            "EGES_f":112
        },
        "31":{
            "CEP_e":406,
            "EGES_e":82,
            "CEP_f":517,
            "EGES_f":112
        },
        "32":{
            "CEP_e":404,
            "EGES_e":81,
            "CEP_f":514,
            "EGES_f":111
        },
        "33":{
            "CEP_e":402,
            "EGES_e":81,
            "CEP_f":512,
            "EGES_f":111
        },
        "34":{
            "CEP_e":400,
            "EGES_e":81,
            "CEP_f":510,
            "EGES_f":111
        },
        "35":{
            "CEP_e":398,
            "EGES_e":81,
            "CEP_f":508,
            "EGES_f":111
        },
        "36":{
            "CEP_e":397,
            "EGES_e":81,
            "CEP_f":507,
            "EGES_f":111
        },
        "37":{
            "CEP_e":395,
            "EGES_e":81,
            "CEP_f":505,
            "EGES_f":111
        },
        "38":{
            "CEP_e":393,
            "EGES_e":81,
            "CEP_f":503,
            "EGES_f":111
        },
        "39":{
            "CEP_e":392,
            "EGES_e":81,
            "CEP_f":502,
            "EGES_f":111
        },
        "40":{
            "CEP_e":390,
            "EGES_e":80,
            "CEP_f":500,
            "EGES_f":110
        }
    },
    "biggerSurface": {
        "CEP_a":70,
        "EGES_a":6,
        "CEP_b":110,
        "EGES_b":11,
        "CEP_c":180,
        "EGES_c":30,
        "CEP_d":250,
        "EGES_d":50,
        "CEP_e":330,
        "EGES_e":70,
        "CEP_f":420,
        "EGES_f":100
    },
    "biggerSurfaceAltitude": {
        "CEP_e":390,
        "EGES_e":80,
        "CEP_f":500,
        "EGES_f":110
    }
 }